billing/__init__.py
billing/admin.py
billing/apps.py
billing/models.py
billing/psp.py
billing/total.py
billing/urls.py
billing/views.py
billing/actions/__init__.py
billing/actions/accounts.py
billing/actions/charges.py
billing/actions/credit_cards.py
billing/actions/invoices.py
billing/management/commands/__init__.py
billing/management/commands/audit_closed_invoices.py
billing/management/commands/create_invoices.py
billing/management/commands/match_funds.py
billing/management/commands/pay_invoices.py
billing/management/commands/update_accounts_delinquent_status.py
billing/migrations/0001_initial.py
billing/migrations/0002_default_currency.py
billing/migrations/0003_psp_uri_to_generic_relation.py
billing/migrations/0004_add_modified_field.py
billing/migrations/0005_creditcard_status.py
billing/migrations/0006_add_product_code_and_properties.py
billing/migrations/0007_payed_to_paid.py
billing/migrations/0008_charge_deleted_and_reverses.py
billing/migrations/0009_longer_product_code.py
billing/migrations/0010_allow_empty_product_property_value.py
billing/migrations/0011_cascade_delete_product_properties.py
billing/migrations/0012_index_deleted_field.py
billing/migrations/0013_replace_past_due_status_by_due_date.py
billing/migrations/0014_deleting_invoice_detaches_charges.py
billing/migrations/0015_auto_20181223_0907.py
billing/migrations/0016_longer_product_code.py
billing/migrations/0017_new_djmoney.py
billing/migrations/0018_delinquent_flag_and_event_log_model.py
billing/migrations/0019_update_delinquent_flag_default_value.py
billing/migrations/0020_update_currency_fields.py
billing/migrations/__init__.py
billing/signals/__init__.py
billing/signals/handlers.py
billing/templates/admin/billing/form.html
django_customer_billing-1.7.24.dist-info/LICENSE
django_customer_billing-1.7.24.dist-info/METADATA
django_customer_billing-1.7.24.dist-info/WHEEL
django_customer_billing-1.7.24.dist-info/top_level.txt
django_customer_billing-1.7.24.dist-info/RECORD
