Metadata-Version: 2.1
Name: django-customer-billing
Version: 1.7.24
Summary: UNKNOWN
Home-page: https://github.com/skioo/django-customer-billing
Author: Nicholas Wolff
Author-email: nwolff@gmail.com
License: MIT
Download-URL: https://pypi.python.org/pypi/django-customer-billing
Platform: UNKNOWN
Classifier: Development Status :: 5 - Production/Stable
Classifier: Environment :: Web Environment
Classifier: Framework :: Django :: 2.2
Classifier: Framework :: Django :: 3.2
Classifier: Intended Audience :: Developers
Classifier: License :: OSI Approved :: MIT License
Classifier: Operating System :: OS Independent
Classifier: Programming Language :: Python
Classifier: Programming Language :: Python :: 3.6
Classifier: Programming Language :: Python :: 3.7
Classifier: Programming Language :: Python :: 3.8
License-File: LICENSE
Requires-Dist: Django (>=2.2)
Requires-Dist: django-money
Requires-Dist: django-fsm
Requires-Dist: djangorestframework
Requires-Dist: django-import-export
Requires-Dist: structlog
Requires-Dist: typing
Requires-Dist: progressbar2
